fibermc/__init__.py
fibermc/estimators.py
fibermc/geometry_utils.py
fibermc/graphics_utils.py
fibermc/implicit_differentiation.py
fibermc/jax_utils.py
fibermc/splines.py
fibermc/utils.py
fibermc-0.0.4.dist-info/METADATA
fibermc-0.0.4.dist-info/WHEEL
fibermc-0.0.4.dist-info/licenses/LICENSE
fibermc-0.0.4.dist-info/RECORD
